cli_tasker/__init__.py
cli_tasker/cli.py
cli_tasker/utils.py
cli_tasker-1.0.1.dist-info/LICENSE
cli_tasker-1.0.1.dist-info/METADATA
cli_tasker-1.0.1.dist-info/WHEEL
cli_tasker-1.0.1.dist-info/entry_points.txt
cli_tasker-1.0.1.dist-info/top_level.txt
cli_tasker-1.0.1.dist-info/RECORD
