Metadata-Version: 2.1
Name: cli-tasker
Version: 1.0.1
Summary: A simple CLI task tracker
Home-page: https://github.com/luyan0422/cli-tasker
Author: 呂佳晏
Author-email: jojojo22845@gmail.com
Classifier: Programming Language :: Python :: 3
Classifier: License :: OSI Approved :: MIT License
Classifier: Operating System :: OS Independent
Requires-Python: >=3.6
License-File: LICENSE
Requires-Dist: tabulate
